israel_open_banking/__init__.py
israel_open_banking/config/__init__.py
israel_open_banking/config/base_config.py
israel_open_banking/core/__init__.py
israel_open_banking/core/ais/README.md
israel_open_banking/core/ais/__init__.py
israel_open_banking/core/ais/general/__init__.py
israel_open_banking/core/ais/general/base.py
israel_open_banking/core/ais/general/enums.py
israel_open_banking/core/ais/general/exceptions.py
israel_open_banking/core/ais/general/models.py
israel_open_banking/core/ais/savings_and_loans/__init__.py
israel_open_banking/core/ais/savings_and_loans/base.py
israel_open_banking/core/ais/savings_and_loans/enums.py
israel_open_banking/core/ais/savings_and_loans/exceptions.py
israel_open_banking/core/ais/savings_and_loans/models.py
israel_open_banking/core/ais/securities/__init__.py
israel_open_banking/core/ais/securities/base.py
israel_open_banking/core/ais/securities/enums.py
israel_open_banking/core/ais/securities/exceptions.py
israel_open_banking/core/ais/securities/models.py
israel_open_banking/core/ais/single_cards/__init__.py
israel_open_banking/core/ais/single_cards/base.py
israel_open_banking/core/ais/single_cards/enums.py
israel_open_banking/core/ais/single_cards/exceptions.py
israel_open_banking/core/ais/single_cards/models.py
israel_open_banking/core/api_endpoints.py
israel_open_banking/core/bank_url_builder.py
israel_open_banking/core/certificates.py
israel_open_banking/core/exceptions.py
israel_open_banking/core/headers.py
israel_open_banking/core/models.py
israel_open_banking/core/oauth/__init__.py
israel_open_banking/core/oauth/base.py
israel_open_banking/core/oauth/exceptions.py
israel_open_banking/core/oauth/models.py
israel_open_banking/core/ssl_adapter.py
israel_open_banking/main.py
israel_open_banking/oauth2/__init__.py
israel_open_banking/oauth2/american_express/__init__.py
israel_open_banking/oauth2/american_express/clients/__init__.py
israel_open_banking/oauth2/american_express/clients/american_express_oauth2_client.py
israel_open_banking-0.3.22.dist-info/LICENSE
israel_open_banking-0.3.22.dist-info/METADATA
israel_open_banking-0.3.22.dist-info/WHEEL
israel_open_banking-0.3.22.dist-info/entry_points.txt
israel_open_banking-0.3.22.dist-info/RECORD
